tails/__init__.py
tails/cli.py
tails/event.py
tails/resource.py
tails/test.py
tails-0.0.1.data/scripts/tails
tails-0.0.1.dist-info/DESCRIPTION.rst
tails-0.0.1.dist-info/METADATA
tails-0.0.1.dist-info/RECORD
tails-0.0.1.dist-info/WHEEL
tails-0.0.1.dist-info/metadata.json
tails-0.0.1.dist-info/top_level.txt
