Metadata-Version: 2.0
Name: tails
Version: 0.0.1
Summary: Utilities for Sanic apps
Home-page: https://github.com/tmacwill/tails
Author: Tommy MacWilliam
Author-email: tmacwilliam@cs.harvard.edu
License: MIT
Keywords: sanic
Platform: UNKNOWN
Classifier: Development Status :: 4 - Beta
Classifier: License :: OSI Approved :: MIT License
Classifier: Intended Audience :: Developers
Classifier: Programming Language :: Python :: 3 :: Only
Requires-Dist: sanic
Requires-Dist: stellata
Requires-Dist: watchdog
